[
    {
        "path": "404.html",
        "type": "file",
        "md5": "a17b7f5df4bc7c8099c45623ebc04814"
    },
    {
        "path": "assets",
        "type": "directory",
        "md5": false
    },
    {
        "path": "assets/css",
        "type": "directory",
        "md5": false
    },
    {
        "path": "/assets/css/editor.css",
        "type": "file",
        "md5": "4202808df745f2ac7ab250606fa0d272"
    },
    {
        "path": "/assets/css/main.css",
        "type": "file",
        "md5": "fa238f48f9a2ab93b0c59a116e831bca"
    },
    {
        "path": "/assets/css/style.css",
        "type": "file",
        "md5": "11bee19e86e8eda2cf9a60efd975666d"
    },
    {
        "path": "assets/dynamic",
        "type": "directory",
        "md5": false
    },
    {
        "path": "assets/js",
        "type": "directory",
        "md5": false
    },
    {
        "path": "/assets/js/scripts.js",
        "type": "file",
        "md5": "e9e5c3efbaa696d1490988cf5b30e23b"
    },
    {
        "path": "/assets/js/scripts.min.js",
        "type": "file",
        "md5": "700105c316933a8202041b6415abb233"
    },
    {
        "path": "/assets/js/svg-fix.js",
        "type": "file",
        "md5": "9b7d020c55e2b4f77ab40c97f88f9ff4"
    },
    {
        "path": "/assets/js/svg-map.js",
        "type": "file",
        "md5": "ff4392540fcf4c3d3f5e03806e112816"
    },
    {
        "path": "assets/svg",
        "type": "directory",
        "md5": false
    },
    {
        "path": "/assets/svg/svg-map.svg",
        "type": "file",
        "md5": "cf04dfd5c3cc64e0be44692fe7d976a6"
    },
    {
        "path": "authors",
        "type": "directory",
        "md5": false
    },
    {
        "path": "authors/mrw",
        "type": "directory",
        "md5": false
    },
    {
        "path": "/authors/mrw/index.html",
        "type": "file",
        "md5": "af68dec4ae23a9bbcde229d7f94b928f"
    },
    {
        "path": "feed.json",
        "type": "file",
        "md5": "613af715373595d0521763a3709f56b3"
    },
    {
        "path": "feed.xml",
        "type": "file",
        "md5": "34018147ec09fb0df00cd95b5c3e5a98"
    },
    {
        "path": "index.html",
        "type": "file",
        "md5": "6570d9fc4d368ec678af6e2f1ab7ed88"
    },
    {
        "path": "robots.txt",
        "type": "file",
        "md5": "48d29ec343b2ef9ac9c421122b1b3a3e"
    },
    {
        "path": "sitemap.xml",
        "type": "file",
        "md5": "6f5c3f55474db73dd06b65ca6d7b5e6e"
    },
    {
        "path": "sitemap.xsl",
        "type": "file",
        "md5": "03c2f9a7fdcc46ff05c435907614a0b8"
    },
    {
        "path": "tags",
        "type": "directory",
        "md5": false
    },
    {
        "path": "/tags/index.html",
        "type": "file",
        "md5": "13a41b13c8a1399fc681bcb0c57de359"
    },
    {
        "path": "tslyh-tlfzywn-fdl-lhlwl-ljmyaa-laatl",
        "type": "directory",
        "md5": false
    },
    {
        "path": "/tslyh-tlfzywn-fdl-lhlwl-ljmyaa-laatl/index.html",
        "type": "file",
        "md5": "3e57fc19d23f4ec3b366d1738395abde"
    },
    {
        "path": "tslyh-tlfzywn-ldlyl-lshml-lhtrfy-llmbtdyyn-wlmhtrfyn",
        "type": "directory",
        "md5": false
    },
    {
        "path": "/tslyh-tlfzywn-ldlyl-lshml-lhtrfy-llmbtdyyn-wlmhtrfyn/index.html",
        "type": "file",
        "md5": "65963becacad0f79f06068b117d3e1c2"
    },
    {
        "path": "tslyh-tlfzywn-lmwswaa-lkml-llsyn-wlslh",
        "type": "directory",
        "md5": false
    },
    {
        "path": "/tslyh-tlfzywn-lmwswaa-lkml-llsyn-wlslh/index.html",
        "type": "file",
        "md5": "f772208c45d4bddb4a8db08d0f9b141a"
    }
]